pybattletank/__init__.py
pybattletank/__main__.py
pybattletank-0.1.0.dist-info/METADATA
pybattletank-0.1.0.dist-info/WHEEL
pybattletank-0.1.0.dist-info/licenses/LICENSE
pybattletank-0.1.0.dist-info/RECORD
